{
  "success":true,
  "rows":[
    {
      "id":"1001",
      "moveType":"TANK_TO_TANK",
      "moveName":"罐付罐",
      "payNode":"13",
      "getNode":"班检尺",
      "startTime":"氧化铝",
      "endTime":"氧化铝",
      "payMaterial":"待检",
      "getMaterial":"罐量",
      "paySubState":"13",
      "getSubState":"165℃",
      "payAgoGauge":"125℃",
      "payLaterGauge":"215ML",
      "getAgoGauge":"215ML",
      "getLaterGauge":"未提交",
      "createBy":"98",
      "createTime":"65",
      "closeBy":"一般",
      "closeTime":"222℃"
    },
    {
      "id":"1002",
      "moveType":"TANK_TO_IOF",
      "moveName":"罐付出厂点",
      "payNode":"13",
      "getNode":"班检尺",
      "startTime":"氧化铝",
      "endTime":"氧化铝",
      "payMaterial":"待检",
      "getMaterial":"罐量",
      "paySubState":"13",
      "getSubState":"165℃",
      "payAgoGauge":"125℃",
      "payLaterGauge":"215ML",
      "getAgoGauge":"215ML",
      "getLaterGauge":"未提交",
      "createBy":"98",
      "createTime":"65",
      "closeBy":"一般",
      "closeTime":"222℃"
    },
    {
      "id":"1003",
      "moveType":"TANK_TO_LINE",
      "moveName":"罐付料线",
      "payNode":"13",
      "getNode":"班检尺",
      "startTime":"氧化铝",
      "endTime":"氧化铝",
      "payMaterial":"待检",
      "getMaterial":"罐量",
      "paySubState":"13",
      "getSubState":"165℃",
      "payAgoGauge":"125℃",
      "payLaterGauge":"215ML",
      "getAgoGauge":"215ML",
      "getLaterGauge":"未提交",
      "createBy":"98",
      "createTime":"65",
      "closeBy":"一般",
      "closeTime":"222℃"
    }
  ]
}

